{
  "project_info": {
    "project_number": "683368371321",
    "project_id": "pushnotification-31d9c",
    "storage_bucket": "pushnotification-31d9c.firebasestorage.app"
  },
  "client": [
    {
      "client_info": {
        "mobilesdk_app_id": "1:683368371321:android:95cc4eecc0afe9794fb0a8",
        "android_client_info": {
          "package_name": "com.example.notification_flutter"
        }
      },
      "oauth_client": [],
      "api_key": [
        {
          "current_key": "AIzaSyCPcjhn-U8nrfRpKOzcqeeWJCQ93NMtUsc"
        }
      ],
      "services": {
        "appinvite_service": {
          "other_platform_oauth_client": []
        }
      }
    }
  ],
  "configuration_version": "1"
}